{
  "120363405611480825@g.us": {
    "2348161262401@s.whatsapp.net": {
      "count": 1,
      "reasons": [
        "@2348161262401 @Mum2"
      ],
      "lastWarned": "2025-10-12T20:42:35.544Z"
    }
  },
  "120363420941246798@g.us": {
    "146905615077588@lid": {
      "count": 2,
      "reasons": [
        "No reason provided",
        "No reason provided"
      ],
      "lastWarned": "2025-10-07T20:19:07.902Z"
    },
    "2347041915568@s.whatsapp.net": {
      "count": 1,
      "reasons": [
        "@2347041915568"
      ],
      "lastWarned": "2025-10-07T20:46:17.419Z"
    },
    "2349116950782@s.whatsapp.net": {
      "count": 3,
      "reasons": [
        "@2349116950782",
        "@2349116950782",
        "@2349116950782"
      ],
      "lastWarned": "2025-10-11T19:10:15.051Z"
    },
    "192170275410019@lid": {
      "count": 1,
      "reasons": [
        "No reason provided"
      ],
      "lastWarned": "2025-10-11T18:11:29.623Z"
    },
    "2348063535051@s.whatsapp.net": {
      "count": 1,
      "reasons": [
        "@2348063535051"
      ],
      "lastWarned": "2025-10-12T20:43:04.651Z"
    },
    "2348141727126@s.whatsapp.net": {
      "count": 1,
      "reasons": [
        "@2348141727126"
      ],
      "lastWarned": "2025-10-12T20:43:24.406Z"
    },
    "2349040480027@s.whatsapp.net": {
      "count": 1,
      "reasons": [
        "@2349040480027"
      ],
      "lastWarned": "2025-10-12T20:43:55.377Z"
    },
    "2349073431724@s.whatsapp.net": {
      "count": 1,
      "reasons": [
        "@2349073431724"
      ],
      "lastWarned": "2025-10-12T20:44:22.275Z"
    },
    "254797824373@s.whatsapp.net": {
      "count": 1,
      "reasons": [
        "@254797824373"
      ],
      "lastWarned": "2025-10-13T08:57:54.645Z"
    },
    "2347080467442@s.whatsapp.net": {
      "count": 1,
      "reasons": [
        "@2347080467442"
      ],
      "lastWarned": "2025-10-13T12:21:36.708Z"
    },
    "109118157238392@lid": {
      "count": 1,
      "reasons": [
        "No reason provided"
      ],
      "lastWarned": "2025-10-13T18:20:26.483Z"
    }
  }
}